{
    "string": [
        {
            "name": "module_desc",
            "value": "module description"
        },
        {
            "name": "EntryAbility_desc",
            "value": "description"
        },
        {
            "name": "EntryAbility_label",
            "value": "label"
        },
        {
            "name": "lorem_ipsum",
            "value": "Lorem ipsum dolor sit amet, consectetur adipiscing elit. Nam in scelerisque sem. Maurisvolutpat, dolor id interdum ullamcorper, risus dolor egestas lectus, sit amet mattis purusdui nec risus. Maecenas non sodales nisi, vel dictum dolor. Class aptent taciti sociosqu adlitora torquent per conubia nostra, per inceptos himenaeos. Suspendisse blandit eleifenddiam, vel rutrum tellus vulputate quis. Aliquam eget libero aliquet, imperdiet nisl a,ornare ex. Sed rhoncus est ut libero porta lobortis. Fusce in dictum tellus.\n\nSuspendisse interdum ornare ante. Aliquam nec cursus lorem. Morbi id magna felis. Vivamusegestas, est a condimentum egestas, turpis nisl iaculis ipsum, in dictum tellus dolor sedneque. Morbi tellus erat, dapibus ut sem a, iaculis tincidunt dui. Interdum et malesuadafames ac ante ipsum primis in faucibus. Curabitur et eros porttitor, ultricies urna vitae,molestie nibh. Phasellus at commodo eros, non aliquet metus. Sed maximus nisl nec dolorbibendum, vel congue leo egestas.\n\nSed interdum tortor nibh, in sagittis risus mollis quis. Curabitur mi odio, condimentum sitamet auctor at, mollis non turpis. Nullam pretium libero vestibulum, finibus orci vel,molestie quam. Fusce blandit tincidunt nulla, quis sollicitudin libero facilisis et. Integerinterdum nunc ligula, et fermentum metus hendrerit id. Vestibulum lectus felis, dictum atlacinia sit amet, tristique id quam. Cras eu consequat dui. Suspendisse sodales nunc ligula,in lobortis sem porta sed. Integer id ultrices magna, in luctus elit. Sed a pellentesqueest.\n\nAenean nunc velit, lacinia sed dolor sed, ultrices viverra nulla. Etiam a venenatis nibh.Morbi laoreet, tortor sed facilisis varius, nibh orci rhoncus nulla, id elementum leo duinon lorem. Nam mollis ipsum quis auctor varius. Quisque elementum eu libero sed commodo. Ineros nisl, imperdiet vel imperdiet et, scelerisque a mauris. Pellentesque varius ex nunc,quis imperdiet eros placerat ac. Duis finibus orci et est auctor tincidunt. Sed non viverraipsum. Nunc quis augue egestas, cursus lorem at, molestie sem. Morbi a consectetur ipsum, aplacerat diam. Etiam vulputate dignissim convallis. Integer faucibus mauris sit amet finibusconvallis.\n\nPhasellus in aliquet mi. Pellentesque habitant morbi tristique senectus et netus etmalesuada fames ac turpis egestas. In volutpat arcu ut felis sagittis, in finibus massagravida. Pellentesque id tellus orci. Integer dictum, lorem sed efficitur ullamcorper,libero justo consectetur ipsum, in mollis nisl ex sed nisl. Donec maximus ullamcorpersodales. Praesent bibendum rhoncus tellus nec feugiat. In a ornare nulla. Donec rhoncuslibero vel nunc consequat, quis tincidunt nisl eleifend. Cras bibendum enim a justo luctusvestibulum. Fusce dictum libero quis erat maximus, vitae volutpat diam dignissim."
        },
        {
            "name": "app_name",
            "value": "javademo"
        },
        {
            "name": "action_settings",
            "value": "Settings"
        },
        {
            "name": "first_fragment_label",
            "value": "First Fragment"
        },
        {
            "name": "second_fragment_label",
            "value": "Second Fragment"
        },
        {
            "name": "next",
            "value": "Next"
        },
        {
            "name": "previous",
            "value": "Previous"
        }
    ]
}